gradysim/__init__.py
gradysim/encapsulator/__init__.py
gradysim/encapsulator/interface.py
gradysim/encapsulator/interop.py
gradysim/encapsulator/python.py
gradysim/protocol/__init__.py
gradysim/protocol/interface.py
gradysim/protocol/position.py
gradysim/protocol/messages/__init__.py
gradysim/protocol/messages/communication.py
gradysim/protocol/messages/mobility.py
gradysim/protocol/messages/telemetry.py
gradysim/protocol/plugin/__init__.py
gradysim/protocol/plugin/dispatcher.py
gradysim/protocol/plugin/follow_mobility.py
gradysim/protocol/plugin/mission_mobility.py
gradysim/protocol/plugin/radio.py
gradysim/protocol/plugin/random_mobility.py
gradysim/protocol/plugin/statistics.py
gradysim/simulator/__init__.py
gradysim/simulator/event.py
gradysim/simulator/log.py
gradysim/simulator/node.py
gradysim/simulator/simulation.py
gradysim/simulator/extension/__init__.py
gradysim/simulator/extension/camera.py
gradysim/simulator/extension/communication_controller.py
gradysim/simulator/extension/extension.py
gradysim/simulator/extension/visualization_controller.py
gradysim/simulator/handler/__init__.py
gradysim/simulator/handler/assertion.py
gradysim/simulator/handler/communication.py
gradysim/simulator/handler/interface.py
gradysim/simulator/handler/mobility.py
gradysim/simulator/handler/timer.py
gradysim/simulator/handler/visualization.py
gradysim-0.7.3.dist-info/licenses/LICENSE.txt
gradysim-0.7.3.dist-info/METADATA
gradysim-0.7.3.dist-info/WHEEL
gradysim-0.7.3.dist-info/top_level.txt
gradysim-0.7.3.dist-info/RECORD
