Metadata-Version: 2.4
Name: gradysim
Version: 0.7.3
Summary: GrADyS-SIM NextGen is a framework for implementing distributed algorithms in a simulated network environment
Author-email: Thiago de Souza Lamenza <thlamenza@hotmail.com>, Josef Maria Kamysek <josef@kamysek.com>
License: MIT License
Project-URL: Homepage, https://github.com/Project-GrADyS/gradys-sim-nextgen
Project-URL: Documentation, https://project-gradys.github.io/gradys-sim-nextgen/
Keywords: network,distributed,algorithm,simulation,gradys,LAC,PUC,drone,sensor
Classifier: Programming Language :: Python :: 3
Classifier: License :: OSI Approved :: MIT License
Classifier: Operating System :: OS Independent
Requires-Python: >=3.8
License-File: LICENSE.txt
Requires-Dist: websockets>=12
Dynamic: license-file
